Workbook

Sheet Valuation Summary
A1: Ryanair Holdings plc (RYAAY) - Equity Valuation Dashboard
A6: Valuation Step / Output Component | B6: Value (€ Millions) | C6: Source
A7: Cumulative Present Value of 5-Yr Cash Flows | B7: =SUM('DCF Model & Data'!E29:I29) -> 9313.9938 | C7: Sum of explicit forecast PV rows (FY2027 - FY2031)
A8: Terminal Value at Year 5 (Un-discounted) | B8: =('DCF Model & Data'!I28*(1+'DCF Model & Data'!B20))/('DCF Model & Data'!$B$19-'DCF Model & Data'!$B$20) -> 38700.741 | C8: (FCFF (Yr 5) * (1 + g))/ (WACC - g)
A9: Present Value of Terminal Value | B9: =B8/((1+'DCF Model & Data'!$B$19)^5) -> 25152.826 | C9: Terminal Value discounted back 5 periods to present day
A10: Total Corporate Enterprise Value | B10: =B7+B9 -> 34466.82 | C10: PV of Explicit Cash Flows + PV of Terminal Value
A11: Add: Net Cash Position (Liquidity Surplus) | B11: ='DCF Model & Data'!B22 -> 2100 | C11: Balance Sheet Net Cash Allocation (FY2026 Audit)
A12: Total Target Equity Value | B12: =B10+B11 -> 36566.82 | C12: Enterprise Value + Net Corporate Liquid Positions
A13: Divided By: Common Shares Outstanding | B13: ='DCF Model & Data'!B21 -> 1055.5 | C13: Total outstanding share pool count
A14: TARGET INTRINSIC PRICE PER SHARE | B14: =B12/B13 -> 34.644074 | C14: Total Equity Value / Outstanding Shares pool

Sheet DCF Model & Data
A1: Ryanair Holdings plc (RYAAY) - Discounted Cash Flow Valuation Model
A6: Line Items | B6: FY-2024 in Millions | C6: FY-2025 in Millions | D6: FY-2026 in Millions
A7: Total Operating Revenue | B7: 13443.8 | C7: 13948.5 | D7: 15544.3
A8: Operating Profit | B8: 2060.7 | C8: 1558 | D8: 2374.2
A9: Profit of the year | B9: 1917.1 | C9: 1611.6 | D9: 2173.7
A11: Depreciation | B11: 1059.5 | C11: 1214.4 | D11: 1373.4
A12: Capital Expenditure | B12: 2391.9 | C12: 1552.5 | D12: 1892.4
A15: I. Valuation Assumptions | C15: Base for these assumptions
A16: Revenue Growth Rate | B16: 0.05 | C16: Previous 3 years data
A17: Target EBIT Margin | B17: 0.153 | C17: FY26 Operating Profit/Operating Revenue
A18: Irish Corporate Tax Rate | B18: 0.125
A19: Weighted Average Cost of Capital (WACC) | B19: 0.09
A20: Terminal Growth Rate (g) | B20: 0.02
A21: Shares Outstanding (Millions) | B21: 1055.5
A22: Net Cash Poisition (Millions) | B22: 2100
A24: II. Financial Analysis and Projections
A25: Line Items (Euros in millions) | B25: FY2024(A) | C25: FY2025(A) | D25: FY2026(A) | E25: FY2027(P) | F25: FY2028(P) | G25: FY2029(P) | H25: FY2030(P) | I25: FY2031(P)
A26: Total Operating Revenue | B26: =B7 -> 13443.8 | C26: =C7 -> 13948.5 | D26: =D7 -> 15544.3 | E26: =D26*(1+$B$16) -> 16321.515 | F26: =E26*(1+$B$16) -> 17137.591 | G26: =F26*(1+$B$16) -> 17994.47 | H26: =G26*(1+$B$16) -> 18894.194 | I26: =H26*(1+$B$16) -> 19838.903
A27: Operating Profit (EBIT) | B27: =B8 -> 2060.7 | C27: =C8 -> 1558 | D27: =D8 -> 2374.2 | E27: =E26*$B$17 -> 2497.1918 | F27: =F26*$B$17 -> 2622.0514 | G27: =G26*$B$17 -> 2753.154 | H27: =H26*$B$17 -> 2890.8117 | I27: =I26*$B$17 -> 3035.3522
A28: Net Operating Profit After Tax (NOPAT / FCFF) | B28: - | C28: - | D28: - | E28: =E27*(1-$B$18) -> 2185.0428 | F28: =F27*(1-$B$18) -> 2294.295 | G28: =G27*(1-$B$18) -> 2409.0097 | H28: =H27*(1-$B$18) -> 2529.4602 | I28: =I27*(1-$B$18) -> 2655.9332
A29: Present Value of FCFF | B29: - | C29: - | D29: - | E29: =E28/(1+$B$19)^1 -> 2004.6264 | F29: =F28/(1+$B$19)^2 -> 1931.0622 | G29: =G28/(1+$B$19)^3 -> 1860.1975 | H29: =H28/(1+$B$19)^4 -> 1791.9334 | I29: =I28/(1+$B$19)^5 -> 1726.1743
A30: Depreciation | B30: =B11 -> 1059.5 | C30: =C11 -> 1214.4 | D30: =D11 -> 1373.4
